chinilla_rs-0.1.20.dist-info/METADATA
chinilla_rs-0.1.20.dist-info/WHEEL
chinilla_rs/__init__.py
chinilla_rs/__init__.pyi
chinilla_rs/py.typed
chinilla_rs/chinilla_rs.cpython-311-x86_64-linux-gnu.so
chinilla_rs-0.1.20.dist-info/RECORD
