Metadata-Version: 2.1
Name: chinilla_rs
Version: 0.1.20
Summary: Code useful for implementing chinilla consensus.
Home-Page: https://github.com/Chinilla/chinilla_rs/
Author: Richard Kiss <him@richardkiss.com>
Author-email: Richard Kiss <him@richardkiss.com>
License: Apache-2.0
Project-URL: Source Code, https://github.com/Chinilla/chinilla_rs/
